{
  "regular": [
    {
      "name": "Screenshot 2025-08-18 205704.png",
      "path": "Happy-Birthday-Dean-/photos/Screenshot 2025-08-18 205704.png"
    }
  ],
  "hidden": [
    {
      "name": "963.PNG",
      "path": "Happy-Birthday-Dean-/photos/hidden/963.PNG"
    },
    {
      "name": "kiss.png",
      "path": "Happy-Birthday-Dean-/photos/hidden/kiss.png"
    },
    {
      "name": "survivor beach date forget = fail.png",
      "path": "Happy-Birthday-Dean-/photos/hidden/survivor beach date forget = fail.png"
    }
  ]
}